Topsis/__init__.py
Topsis/topsis.py
topsispypi-0.0.1.dist-info/METADATA
topsispypi-0.0.1.dist-info/WHEEL
topsispypi-0.0.1.dist-info/top_level.txt
topsispypi-0.0.1.dist-info/RECORD
