Metadata-Version: 2.1
Name: topsispypi
Version: 0.0.1
Summary: A Topsis Package
Home-page: UNKNOWN
Author: Tanishq Singla
Author-email: <tanishqsingla08@gmail.com>
License: UNKNOWN
Keywords: python,video,stream,video stream,camera stream,sockets
Platform: UNKNOWN
Classifier: Development Status :: 1 - Planning
Classifier: Intended Audience :: Developers
Classifier: Programming Language :: Python :: 3
Classifier: Operating System :: Unix
Classifier: Operating System :: MacOS :: MacOS X
Classifier: Operating System :: Microsoft :: Windows
Requires-Dist: numpy
Requires-Dist: pandas
Requires-Dist: sys
